{
    "os": "macOS-10.16-x86_64-i386-64bit",
    "python": "3.8.5",
    "heartbeatAt": "2020-12-12T17:39:14.284108",
    "startedAt": "2020-12-12T17:39:13.031158",
    "docker": null,
    "cpu_count": 8,
    "cuda": null,
    "args": [],
    "state": "running",
    "codePath": "PPO/main_atari.py",
    "program": "main_atari.py",
    "git": {
        "remote": "https://github.com/DarylRodrigo/rl_lib.git",
        "commit": "ad9d229bf6a8abac9e6c27ac07823a06202ea951"
    },
    "email": null,
    "root": "/Users/darylrodrigo/Documents/projects/rl_lib",
    "host": "Daryls-MacBook-Pro.local",
    "username": "darylrodrigo",
    "executable": "/usr/local/opt/python@3.8/bin/python3.8"
}
